{
  "executionId": "EXE-9BFD6900",
  "request": {
    "id": "invoke-mrpy2i4k",
    "type": "update_backlog_status",
    "params": {
      "taskId": "${eventData.taskId}",
      "fromState": "em implementação",
      "toState": "em validação"
    }
  },
  "executionHash": "357e8c46e9a331c3",
  "status": "completed",
  "startedAt": "2026-07-18T05:46:51.332Z",
  "result": "success",
  "output": {
    "success": false,
    "message": "Task ${eventData.taskId} not found in BACKLOG.md"
  },
  "completedAt": "2026-07-18T05:46:51.339Z",
  "duration": 6
}